[
  {
    "date": "Jan 4",
    "day": "Sat",
    "opponent": "Florida",
    "logo": "florida.png",
    "location": "Home - Rupp Arena",
    "venue": "home",
    "time": "11:00 AM ET",
    "result": "W 106-100",
    "conference": true,
    "opponentRank": 0,
    "title": null,
    "exh": false
  },
  {
    "date": "Jan 7",
    "day": "Tue",
    "opponent": "Georgia",
    "logo": "georgia.png",
    "location": "Away - Stegeman Coliseum, Athens, GA",
    "venue": "away",
    "time": "7:00 PM ET",
    "result": "L 69-82",
    "conference": true,
    "opponentRank": 0,
    "title": null,
    "exh": false
  },
  {
    "date": "Jan 11",
    "day": "Sat",
    "opponent": "Mississippi State",
    "logo": "mississippi-state.png",
    "location": "Away - Humphrey Coliseum, Starkville, MS",
    "venue": "away",
    "time": "8:30 PM ET",
    "result": "W 95-90",
    "conference": true,
    "opponentRank": 0,
    "title": null,
    "exh": false
  },
  {
    "date": "Jan 14",
    "day": "Tue",
    "opponent": "Texas A&M",
    "logo": "texas-aandm.png",
    "location": "Home - Rupp Arena",
    "venue": "home",
    "time": "7:00 PM ET",
    "result": "W 81-69",
    "conference": true,
    "opponentRank": 0,
    "title": null,
    "exh": false
  },
  {
    "date": "Jan 18",
    "day": "Sat",
    "opponent": "Alabama",
    "logo": "alabama.png",
    "location": "Home - Rupp Arena",
    "venue": "home",
    "time": "12:00 PM ET",
    "result": "L 97-102",
    "conference": true,
    "opponentRank": 0,
    "title": null,
    "exh": false
  },
  {
    "date": "Jan 25",
    "day": "Sat",
    "opponent": "Vanderbilt",
    "logo": "vanderbilt.png",
    "location": "Away - Memorial Gymnasium (TN), Nashville, TN",
    "venue": "away",
    "time": "2:30 PM ET",
    "result": "L 69-74",
    "conference": true,
    "opponentRank": 0,
    "title": null,
    "exh": false
  },
  {
    "date": "Jan 28",
    "day": "Tue",
    "opponent": "Tennessee",
    "logo": "tennessee.png",
    "location": "Away - Food City Center, Knoxville, TN",
    "venue": "away",
    "time": "7:00 PM ET",
    "result": "W 78-73",
    "conference": true,
    "opponentRank": 0,
    "title": null,
    "exh": false
  },
  {
    "date": "Feb 1",
    "day": "Sat",
    "opponent": "Arkansas",
    "logo": "arkansas.png",
    "location": "Home - Rupp Arena",
    "venue": "home",
    "time": "9:00 PM ET",
    "result": "L 79-89",
    "conference": true,
    "opponentRank": 0,
    "title": null,
    "exh": false
  },
  {
    "date": "Feb 4",
    "day": "Tue",
    "opponent": "Ole Miss",
    "logo": "ole-miss.png",
    "location": "Away - The Sandy and John Black Pavilion at Ole Miss, Oxford, MS",
    "venue": "away",
    "time": "7:00 PM ET",
    "result": "L 84-98",
    "conference": true,
    "opponentRank": 0,
    "title": null,
    "exh": false
  },
  {
    "date": "Feb 8",
    "day": "Sat",
    "opponent": "South Carolina",
    "logo": "south-carolina.png",
    "location": "Home - Rupp Arena",
    "venue": "home",
    "time": "12:00 PM ET",
    "result": "W 80-57",
    "conference": true,
    "opponentRank": 0,
    "title": null,
    "exh": false
  },
  {
    "date": "Feb 11",
    "day": "Tue",
    "opponent": "Tennessee",
    "logo": "tennessee.png",
    "location": "Home - Rupp Arena",
    "venue": "home",
    "time": "7:00 PM ET",
    "result": "W 75-64",
    "conference": true,
    "opponentRank": 0,
    "title": null,
    "exh": false
  },
  {
    "date": "Feb 15",
    "day": "Sat",
    "opponent": "Texas",
    "logo": "texas.png",
    "location": "Away - Moody Center, Austin, TX",
    "venue": "away",
    "time": "8:00 PM ET",
    "result": "L 78-82",
    "conference": true,
    "opponentRank": 0,
    "title": null,
    "exh": false
  },
  {
    "date": "Feb 19",
    "day": "Wed",
    "opponent": "Vanderbilt",
    "logo": "vanderbilt.png",
    "location": "Home - Rupp Arena",
    "venue": "home",
    "time": "7:00 PM ET",
    "result": "W 82-61",
    "conference": true,
    "opponentRank": 0,
    "title": null,
    "exh": false
  },
  {
    "date": "Feb 22",
    "day": "Sat",
    "opponent": "Alabama",
    "logo": "alabama.png",
    "location": "Away - Coleman Coliseum, Tuscaloosa, AL",
    "venue": "away",
    "time": "6:10 PM ET",
    "result": "L 83-96",
    "conference": true,
    "opponentRank": 0,
    "title": null,
    "exh": false
  },
  {
    "date": "Feb 26",
    "day": "Wed",
    "opponent": "Oklahoma",
    "logo": "oklahoma.png",
    "location": "Away - Lloyd Noble Center, Norman, OK",
    "venue": "away",
    "time": "9:00 PM ET",
    "result": "W 83-82",
    "conference": true,
    "opponentRank": 0,
    "title": null,
    "exh": false
  },
  {
    "date": "Mar 1",
    "day": "Sat",
    "opponent": "Auburn",
    "logo": "auburn.png",
    "location": "Home - Rupp Arena",
    "venue": "home",
    "time": "1:00 PM ET",
    "result": "L 78-94",
    "conference": true,
    "opponentRank": 0,
    "title": null,
    "exh": false
  },
  {
    "date": "Mar 4",
    "day": "Tue",
    "opponent": "LSU",
    "logo": "lsu.png",
    "location": "Home - Rupp Arena",
    "venue": "home",
    "time": "7:00 PM ET",
    "result": "W 95-64",
    "conference": true,
    "opponentRank": 0,
    "title": null,
    "exh": false
  },
  {
    "date": "Mar 8",
    "day": "Sat",
    "opponent": "Missouri",
    "logo": "missouri.png",
    "location": "Away - Mizzou Arena, Columbia, MO",
    "venue": "away",
    "time": "12:00 PM ET",
    "result": "W 91-83",
    "conference": true,
    "opponentRank": 0,
    "title": null,
    "exh": false
  },
  {
    "date": "Mar 13",
    "day": "Thu",
    "opponent": "Oklahoma",
    "logo": "oklahoma.png",
    "location": "Neutral - Bridgestone Arena, Nashville, TN",
    "venue": "neutral",
    "time": "9:45 PM ET",
    "result": "W 85-84",
    "conference": true,
    "opponentRank": 0,
    "title": "SEC Tournament - 2nd Round",
    "exh": false
  },
  {
    "date": "Mar 14",
    "day": "Fri",
    "opponent": "Alabama",
    "logo": "alabama.png",
    "location": "Neutral - Bridgestone Arena, Nashville, TN",
    "venue": "neutral",
    "time": "8:52 PM ET",
    "result": "L 70-99",
    "conference": true,
    "opponentRank": 0,
    "title": "SEC Tournament - Quarterfinal",
    "exh": false
  },
  {
    "date": "Mar 21",
    "day": "Fri",
    "opponent": "Troy",
    "logo": "troy.png",
    "location": "Neutral - Fiserv Forum, Milwaukee, WI",
    "venue": "neutral",
    "time": "6:20 PM ET",
    "result": "W 76-57",
    "conference": false,
    "opponentRank": 0,
    "title": "Men's Basketball Championship - Midwest Region - 1st Round",
    "exh": false
  },
  {
    "date": "Mar 23",
    "day": "Sun",
    "opponent": "Illinois",
    "logo": "illinois.png",
    "location": "Neutral - Fiserv Forum, Milwaukee, WI",
    "venue": "neutral",
    "time": "4:30 PM ET",
    "result": "W 84-75",
    "conference": false,
    "opponentRank": 0,
    "title": "Men's Basketball Championship - Midwest Region - 2nd Round",
    "exh": false
  },
  {
    "date": "Mar 28",
    "day": "Fri",
    "opponent": "Tennessee",
    "logo": "tennessee.png",
    "location": "Neutral - Lucas Oil Stadium, Indianapolis, IN",
    "venue": "neutral",
    "time": "6:39 PM ET",
    "result": "L 65-78",
    "conference": false,
    "opponentRank": 0,
    "title": "Men's Basketball Championship - Midwest Region - Sweet 16",
    "exh": false
  },
  {
    "date": "Nov 4",
    "day": "Mon",
    "opponent": "Wright State",
    "logo": "wright-state.png",
    "location": "Home - Rupp Arena",
    "venue": "home",
    "time": "7:00 PM ET",
    "result": "W 103-62",
    "conference": false,
    "opponentRank": 0,
    "title": null,
    "exh": false
  },
  {
    "date": "Nov 9",
    "day": "Sat",
    "opponent": "Bucknell",
    "logo": "bucknell.png",
    "location": "Home - Rupp Arena",
    "venue": "home",
    "time": "4:00 PM ET",
    "result": "W 100-72",
    "conference": false,
    "opponentRank": 0,
    "title": null,
    "exh": false
  },
  {
    "date": "Nov 12",
    "day": "Tue",
    "opponent": "Duke",
    "logo": "duke.png",
    "location": "Neutral - State Farm Arena, Atlanta, GA",
    "venue": "neutral",
    "time": "9:00 PM ET",
    "result": "W 77-72",
    "conference": false,
    "opponentRank": 0,
    "title": "State Farm Champions Classic",
    "exh": false
  },
  {
    "date": "Nov 19",
    "day": "Tue",
    "opponent": "Lipscomb",
    "logo": "lipscomb.png",
    "location": "Home - Rupp Arena",
    "venue": "home",
    "time": "7:00 PM ET",
    "result": "W 97-68",
    "conference": false,
    "opponentRank": 0,
    "title": "BBN Invitational",
    "exh": false
  },
  {
    "date": "Nov 22",
    "day": "Fri",
    "opponent": "Jackson State",
    "logo": "jackson-state.png",
    "location": "Home - Rupp Arena",
    "venue": "home",
    "time": "7:00 PM ET",
    "result": "W 108-59",
    "conference": false,
    "opponentRank": 0,
    "title": "BBN Invitational",
    "exh": false
  },
  {
    "date": "Nov 26",
    "day": "Tue",
    "opponent": "Western Kentucky",
    "logo": "western-kentucky.png",
    "location": "Home - Rupp Arena",
    "venue": "home",
    "time": "6:30 PM ET",
    "result": "W 87-68",
    "conference": false,
    "opponentRank": 0,
    "title": "BBN Invitational",
    "exh": false
  },
  {
    "date": "Nov 29",
    "day": "Fri",
    "opponent": "Georgia State",
    "logo": "georgia-state.png",
    "location": "Home - Rupp Arena",
    "venue": "home",
    "time": "7:00 PM ET",
    "result": "W 105-76",
    "conference": false,
    "opponentRank": 0,
    "title": null,
    "exh": false
  },
  {
    "date": "Dec 3",
    "day": "Tue",
    "opponent": "Clemson",
    "logo": "clemson.png",
    "location": "Away - Littlejohn Coliseum, Clemson, SC",
    "venue": "away",
    "time": "9:30 PM ET",
    "result": "L 66-70",
    "conference": false,
    "opponentRank": 0,
    "title": "SEC/ACC Men's Challenge Presented by Continental Tire",
    "exh": false
  },
  {
    "date": "Dec 7",
    "day": "Sat",
    "opponent": "Gonzaga",
    "logo": "gonzaga.png",
    "location": "Neutral - Climate Pledge Arena, Seattle, WA",
    "venue": "neutral",
    "time": "10:00 PM ET",
    "result": "W 90-89",
    "conference": false,
    "opponentRank": 0,
    "title": "Battle in Seattle",
    "exh": false
  },
  {
    "date": "Dec 11",
    "day": "Wed",
    "opponent": "Colgate",
    "logo": "colgate.png",
    "location": "Home - Rupp Arena",
    "venue": "home",
    "time": "8:00 PM ET",
    "result": "W 78-67",
    "conference": false,
    "opponentRank": 0,
    "title": null,
    "exh": false
  },
  {
    "date": "Dec 14",
    "day": "Sat",
    "opponent": "Louisville",
    "logo": "louisville.png",
    "location": "Home - Rupp Arena",
    "venue": "home",
    "time": "5:15 PM ET",
    "result": "W 93-85",
    "conference": false,
    "opponentRank": 0,
    "title": null,
    "exh": false
  },
  {
    "date": "Dec 21",
    "day": "Sat",
    "opponent": "Ohio State",
    "logo": "ohio-state.png",
    "location": "Neutral - Madison Square Garden, New York, NY",
    "venue": "neutral",
    "time": "5:30 PM ET",
    "result": "L 65-85",
    "conference": false,
    "opponentRank": 0,
    "title": "CBS Sports Classic",
    "exh": false
  },
  {
    "date": "Dec 31",
    "day": "Tue",
    "opponent": "Brown",
    "logo": "brown.png",
    "location": "Home - Rupp Arena",
    "venue": "home",
    "time": "2:00 PM ET",
    "result": "W 88-54",
    "conference": false,
    "opponentRank": 0,
    "title": null,
    "exh": false
  }
]